setup.py
upcloud/__init__.py
upcloud/cli.py
upcloud/color.py
upcloud/main.py
upcloud/manual.py
upcloud/upcloud.py
upcloud.egg-info/PKG-INFO
upcloud.egg-info/SOURCES.txt
upcloud.egg-info/dependency_links.txt
upcloud.egg-info/entry_points.txt
upcloud.egg-info/requires.txt
upcloud.egg-info/top_level.txt