Metadata-Version: 1.1
Name: upcloud
Version: 0.1.6
Summary: manage your bucket of UpYun
Home-page: https://github.com/kehr/upcloud
Author: kehr (kaixuan wang)
Author-email: kehr.china@gmail.com
License: License :: OSI Approved :: MIT License
Keywords: upyun,upcloud,python,client
Platform: Platform Independent
Classifier: Development Status :: 4 - Beta
Classifier: Environment :: Console
Classifier: Intended Audience :: Developers
Classifier: License :: OSI Approved :: MIT License
Classifier: Operating System :: OS Independent
Classifier: Programming Language :: Python
Classifier: Programming Language :: Python :: 2
Classifier: Programming Language :: Python :: 2.6
Classifier: Programming Language :: Python :: 2.7
Classifier: Programming Language :: Python :: 3
Classifier: Programming Language :: Python :: 3.3
Classifier: Topic :: Software Development
Classifier: Topic :: Utilities
